{
  "ids": true,
  "bin": [
    {"id":   2,"method": "equi-width","numbins": 1600},
    {"id":   3,"method": "equi-width","numbins": 1600},
    {"id":   4,"method": "equi-width","numbins": 1600},
    {"id":   5,"method": "equi-width","numbins": 1600},
    {"id":   6,"method": "equi-width","numbins": 1600},
    {"id":   7,"method": "equi-width","numbins": 1600},
    {"id":   8,"method": "equi-width","numbins": 1600},
    {"id":   9,"method": "equi-width","numbins": 1600},
    {"id":  10,"method": "equi-width","numbins": 1600},
    {"id":  11,"method": "equi-width","numbins": 1600},
    {"id":  12,"method": "equi-width","numbins": 1600},
    {"id":  13,"method": "equi-width","numbins": 1600},
    {"id":  14,"method": "equi-width","numbins": 1600},
    {"id":  15,"method": "equi-width","numbins": 1600},
    {"id":  16,"method": "equi-width","numbins": 1600},
    {"id":  17,"method": "equi-width","numbins": 1600},
    {"id":  18,"method": "equi-width","numbins": 1600},
    {"id":  19,"method": "equi-width","numbins": 1600},
    {"id":  20,"method": "equi-width","numbins": 1600},
    {"id":  21,"method": "equi-width","numbins": 1600},
    {"id":  22,"method": "equi-width","numbins": 1600},
    {"id":  23,"method": "equi-width","numbins": 1600},
    {"id":  24,"method": "equi-width","numbins": 1600},
    {"id":  25,"method": "equi-width","numbins": 1600},
    {"id":  26,"method": "equi-width","numbins": 1600},
    {"id":  27,"method": "equi-width","numbins": 1600},
    {"id":  28,"method": "equi-width","numbins": 1600},
    {"id":  29,"method": "equi-width","numbins": 1600},
    {"id":  30,"method": "equi-width","numbins": 1600},
    {"id":  31,"method": "equi-width","numbins": 1600},
    {"id":  32,"method": "equi-width","numbins": 1600},
    {"id":  33,"method": "equi-width","numbins": 1600},
    {"id":  34,"method": "equi-width","numbins": 1600},
    {"id":  35,"method": "equi-width","numbins": 1600},
    {"id":  36,"method": "equi-width","numbins": 1600},
    {"id":  37,"method": "equi-width","numbins": 1600},
    {"id":  38,"method": "equi-width","numbins": 1600},
    {"id":  39,"method": "equi-width","numbins": 1600},
    {"id":  40,"method": "equi-width","numbins": 1600},
    {"id":  41,"method": "equi-width","numbins": 1600},
    {"id":  42,"method": "equi-width","numbins": 1600},
    {"id":  43,"method": "equi-width","numbins": 1600},
    {"id":  44,"method": "equi-width","numbins": 1600},
    {"id":  45,"method": "equi-width","numbins": 1600},
    {"id":  46,"method": "equi-width","numbins": 1600},
    {"id":  47,"method": "equi-width","numbins": 1600},
    {"id":  48,"method": "equi-width","numbins": 1600},
    {"id":  49,"method": "equi-width","numbins": 1600},
    {"id":  50,"method": "equi-width","numbins": 1600},
    {"id":  51,"method": "equi-width","numbins": 1600},
    {"id":  52,"method": "equi-width","numbins": 1600},
    {"id":  53,"method": "equi-width","numbins": 1600},
    {"id":  54,"method": "equi-width","numbins": 1600},
    {"id":  55,"method": "equi-width","numbins": 1600},
    {"id":  56,"method": "equi-width","numbins": 1600},
    {"id":  57,"method": "equi-width","numbins": 1600},
    {"id":  58,"method": "equi-width","numbins": 1600},
    {"id":  59,"method": "equi-width","numbins": 1600},
    {"id":  60,"method": "equi-width","numbins": 1600},
    {"id":  61,"method": "equi-width","numbins": 1600},
    {"id":  62,"method": "equi-width","numbins": 1600},
    {"id":  63,"method": "equi-width","numbins": 1600},
    {"id":  64,"method": "equi-width","numbins": 1600},
    {"id":  65,"method": "equi-width","numbins": 1600},
    {"id":  66,"method": "equi-width","numbins": 1600},
    {"id":  67,"method": "equi-width","numbins": 1600},
    {"id":  68,"method": "equi-width","numbins": 1600},
    {"id":  69,"method": "equi-width","numbins": 1600},
    {"id":  70,"method": "equi-width","numbins": 1600},
    {"id":  71,"method": "equi-width","numbins": 1600},
    {"id":  72,"method": "equi-width","numbins": 1600},
    {"id":  73,"method": "equi-width","numbins": 1600},
    {"id":  74,"method": "equi-width","numbins": 1600},
    {"id":  75,"method": "equi-width","numbins": 1600},
    {"id":  76,"method": "equi-width","numbins": 1600},
    {"id":  77,"method": "equi-width","numbins": 1600},
    {"id":  78,"method": "equi-width","numbins": 1600},
    {"id":  79,"method": "equi-width","numbins": 1600},
    {"id":  80,"method": "equi-width","numbins": 1600},
    {"id":  81,"method": "equi-width","numbins": 1600},
    {"id":  82,"method": "equi-width","numbins": 1600},
    {"id":  83,"method": "equi-width","numbins": 1600},
    {"id":  84,"method": "equi-width","numbins": 1600},
    {"id":  85,"method": "equi-width","numbins": 1600},
    {"id":  86,"method": "equi-width","numbins": 1600},
    {"id":  87,"method": "equi-width","numbins": 1600},
    {"id":  88,"method": "equi-width","numbins": 1600},
    {"id":  89,"method": "equi-width","numbins": 1600},
    {"id":  90,"method": "equi-width","numbins": 1600},
    {"id":  91,"method": "equi-width","numbins": 1600},
    {"id":  92,"method": "equi-width","numbins": 1600},
    {"id":  93,"method": "equi-width","numbins": 1600},
    {"id":  94,"method": "equi-width","numbins": 1600},
    {"id":  95,"method": "equi-width","numbins": 1600},
    {"id":  96,"method": "equi-width","numbins": 1600},
    {"id":  97,"method": "equi-width","numbins": 1600},
    {"id":  98,"method": "equi-width","numbins": 1600},
    {"id":  99,"method": "equi-width","numbins": 1600},
    {"id": 100,"method": "equi-width","numbins": 1600},
    {"id": 101,"method": "equi-width","numbins": 1600},
    {"id": 102,"method": "equi-width","numbins": 1600},
    {"id": 103,"method": "equi-width","numbins": 1600},
    {"id": 104,"method": "equi-width","numbins": 1600},
    {"id": 105,"method": "equi-width","numbins": 1600},
    {"id": 106,"method": "equi-width","numbins": 1600},
    {"id": 107,"method": "equi-width","numbins": 1600},
    {"id": 108,"method": "equi-width","numbins": 1600},
    {"id": 109,"method": "equi-width","numbins": 1600},
    {"id": 110,"method": "equi-width","numbins": 1600},
    {"id": 111,"method": "equi-width","numbins": 1600},
    {"id": 112,"method": "equi-width","numbins": 1600},
    {"id": 113,"method": "equi-width","numbins": 1600},
    {"id": 114,"method": "equi-width","numbins": 1600},
    {"id": 115,"method": "equi-width","numbins": 1600},
    {"id": 116,"method": "equi-width","numbins": 1600},
    {"id": 117,"method": "equi-width","numbins": 1600},
    {"id": 118,"method": "equi-width","numbins": 1600},
    {"id": 119,"method": "equi-width","numbins": 1600},
    {"id": 120,"method": "equi-width","numbins": 1600},
    {"id": 121,"method": "equi-width","numbins": 1600},
    {"id": 122,"method": "equi-width","numbins": 1600},
    {"id": 123,"method": "equi-width","numbins": 1600},
    {"id": 124,"method": "equi-width","numbins": 1600},
    {"id": 125,"method": "equi-width","numbins": 1600},
    {"id": 126,"method": "equi-width","numbins": 1600},
    {"id": 127,"method": "equi-width","numbins": 1600},
    {"id": 128,"method": "equi-width","numbins": 1600},
    {"id": 129,"method": "equi-width","numbins": 1600},
    {"id": 130,"method": "equi-width","numbins": 1600},
    {"id": 131,"method": "equi-width","numbins": 1600},
    {"id": 132,"method": "equi-width","numbins": 1600},
    {"id": 133,"method": "equi-width","numbins": 1600},
    {"id": 134,"method": "equi-width","numbins": 1600},
    {"id": 135,"method": "equi-width","numbins": 1600},
    {"id": 136,"method": "equi-width","numbins": 1600},
    {"id": 137,"method": "equi-width","numbins": 1600},
    {"id": 138,"method": "equi-width","numbins": 1600},
    {"id": 139,"method": "equi-width","numbins": 1600},
    {"id": 140,"method": "equi-width","numbins": 1600},
    {"id": 141,"method": "equi-width","numbins": 1600},
    {"id": 142,"method": "equi-width","numbins": 1600},
    {"id": 143,"method": "equi-width","numbins": 1600},
    {"id": 144,"method": "equi-width","numbins": 1600},
    {"id": 145,"method": "equi-width","numbins": 1600},
    {"id": 146,"method": "equi-width","numbins": 1600},
    {"id": 147,"method": "equi-width","numbins": 1600},
    {"id": 148,"method": "equi-width","numbins": 1600},
    {"id": 149,"method": "equi-width","numbins": 1600},
    {"id": 150,"method": "equi-width","numbins": 1600},
    {"id": 151,"method": "equi-width","numbins": 1600},
    {"id": 152,"method": "equi-width","numbins": 1600},
    {"id": 153,"method": "equi-width","numbins": 1600},
    {"id": 154,"method": "equi-width","numbins": 1600},
    {"id": 155,"method": "equi-width","numbins": 1600},
    {"id": 156,"method": "equi-width","numbins": 1600},
    {"id": 157,"method": "equi-width","numbins": 1600},
    {"id": 158,"method": "equi-width","numbins": 1600},
    {"id": 159,"method": "equi-width","numbins": 1600},
    {"id": 160,"method": "equi-width","numbins": 1600},
    {"id": 161,"method": "equi-width","numbins": 1600},
    {"id": 162,"method": "equi-width","numbins": 1600},
    {"id": 163,"method": "equi-width","numbins": 1600},
    {"id": 164,"method": "equi-width","numbins": 1600},
    {"id": 165,"method": "equi-width","numbins": 1600},
    {"id": 166,"method": "equi-width","numbins": 1600},
    {"id": 167,"method": "equi-width","numbins": 1600},
    {"id": 168,"method": "equi-width","numbins": 1600},
    {"id": 169,"method": "equi-width","numbins": 1600},
    {"id": 170,"method": "equi-width","numbins": 1600},
    {"id": 171,"method": "equi-width","numbins": 1600},
    {"id": 172,"method": "equi-width","numbins": 1600},
    {"id": 173,"method": "equi-width","numbins": 1600},
    {"id": 174,"method": "equi-width","numbins": 1600},
    {"id": 175,"method": "equi-width","numbins": 1600},
    {"id": 176,"method": "equi-width","numbins": 1600},
    {"id": 177,"method": "equi-width","numbins": 1600},
    {"id": 178,"method": "equi-width","numbins": 1600},
    {"id": 179,"method": "equi-width","numbins": 1600},
    {"id": 180,"method": "equi-width","numbins": 1600},
    {"id": 181,"method": "equi-width","numbins": 1600},
    {"id": 182,"method": "equi-width","numbins": 1600},
    {"id": 183,"method": "equi-width","numbins": 1600},
    {"id": 184,"method": "equi-width","numbins": 1600},
    {"id": 185,"method": "equi-width","numbins": 1600},
    {"id": 186,"method": "equi-width","numbins": 1600},
    {"id": 187,"method": "equi-width","numbins": 1600},
    {"id": 188,"method": "equi-width","numbins": 1600},
    {"id": 189,"method": "equi-width","numbins": 1600},
    {"id": 190,"method": "equi-width","numbins": 1600},
    {"id": 191,"method": "equi-width","numbins": 1600},
    {"id": 192,"method": "equi-width","numbins": 1600},
    {"id": 193,"method": "equi-width","numbins": 1600},
    {"id": 194,"method": "equi-width","numbins": 1600},
    {"id": 195,"method": "equi-width","numbins": 1600},
    {"id": 196,"method": "equi-width","numbins": 1600},
    {"id": 197,"method": "equi-width","numbins": 1600},
    {"id": 198,"method": "equi-width","numbins": 1600},
    {"id": 199,"method": "equi-width","numbins": 1600},
    {"id": 200,"method": "equi-width","numbins": 1600},
    {"id": 201,"method": "equi-width","numbins": 1600}
  ]
}