{
  "ids": true,
  "bin": [
    {
      "id": 2,
      "method": "equi-height",
      "numbins": 100
    },
    {
      "id": 3,
      "method": "equi-height",
      "numbins": 100
    },
    {
      "id": 4,
      "method": "equi-height",
      "numbins": 100
    },
    {
      "id": 5,
      "method": "equi-height",
      "numbins": 100
    },
    {
      "id": 6,
      "method": "equi-height",
      "numbins": 100
    },
    {
      "id": 7,
      "method": "equi-height",
      "numbins": 100
    },
    {
      "id": 8,
      "method": "equi-height",
      "numbins": 100
    },
    {
      "id": 9,
      "method": "equi-height",
      "numbins": 100
    },
    {
      "id": 10,
      "method": "equi-height",
      "numbins": 100
    },
    {
      "id": 11,
      "method": "equi-height",
      "numbins": 100
    },
    {
      "id": 12,
      "method": "equi-height",
      "numbins": 100
    },
    {
      "id": 13,
      "method": "equi-height",
      "numbins": 100
    },
    {
      "id": 14,
      "method": "equi-height",
      "numbins": 100
    },
    {
      "id": 15,
      "method": "equi-height",
      "numbins": 100
    },
    {
      "id": 16,
      "method": "equi-height",
      "numbins": 100
    },
    {
      "id": 17,
      "method": "equi-height",
      "numbins": 100
    },
    {
      "id": 18,
      "method": "equi-height",
      "numbins": 100
    },
    {
      "id": 19,
      "method": "equi-height",
      "numbins": 100
    },
    {
      "id": 20,
      "method": "equi-height",
      "numbins": 100
    },
    {
      "id": 21,
      "method": "equi-height",
      "numbins": 100
    },
    {
      "id": 22,
      "method": "equi-height",
      "numbins": 100
    },
    {
      "id": 23,
      "method": "equi-height",
      "numbins": 100
    },
    {
      "id": 24,
      "method": "equi-height",
      "numbins": 100
    },
    {
      "id": 25,
      "method": "equi-height",
      "numbins": 100
    },
    {
      "id": 26,
      "method": "equi-height",
      "numbins": 100
    },
    {
      "id": 27,
      "method": "equi-height",
      "numbins": 100
    },
    {
      "id": 28,
      "method": "equi-height",
      "numbins": 100
    },
    {
      "id": 29,
      "method": "equi-height",
      "numbins": 100
    },
    {
      "id": 30,
      "method": "equi-height",
      "numbins": 100
    },
    {
      "id": 31,
      "method": "equi-height",
      "numbins": 100
    },
    {
      "id": 32,
      "method": "equi-height",
      "numbins": 100
    },
    {
      "id": 33,
      "method": "equi-height",
      "numbins": 100
    },
    {
      "id": 34,
      "method": "equi-height",
      "numbins": 100
    },
    {
      "id": 35,
      "method": "equi-height",
      "numbins": 100
    },
    {
      "id": 36,
      "method": "equi-height",
      "numbins": 100
    },
    {
      "id": 37,
      "method": "equi-height",
      "numbins": 100
    },
    {
      "id": 38,
      "method": "equi-height",
      "numbins": 100
    },
    {
      "id": 39,
      "method": "equi-height",
      "numbins": 100
    },
    {
      "id": 40,
      "method": "equi-height",
      "numbins": 100
    },
    {
      "id": 41,
      "method": "equi-height",
      "numbins": 100
    },
    {
      "id": 42,
      "method": "equi-height",
      "numbins": 100
    },
    {
      "id": 43,
      "method": "equi-height",
      "numbins": 100
    },
    {
      "id": 44,
      "method": "equi-height",
      "numbins": 100
    },
    {
      "id": 45,
      "method": "equi-height",
      "numbins": 100
    },
    {
      "id": 46,
      "method": "equi-height",
      "numbins": 100
    },
    {
      "id": 47,
      "method": "equi-height",
      "numbins": 100
    },
    {
      "id": 48,
      "method": "equi-height",
      "numbins": 100
    },
    {
      "id": 49,
      "method": "equi-height",
      "numbins": 100
    },
    {
      "id": 50,
      "method": "equi-height",
      "numbins": 100
    },
    {
      "id": 51,
      "method": "equi-height",
      "numbins": 100
    },
    {
      "id": 52,
      "method": "equi-height",
      "numbins": 100
    },
    {
      "id": 53,
      "method": "equi-height",
      "numbins": 100
    },
    {
      "id": 54,
      "method": "equi-height",
      "numbins": 100
    },
    {
      "id": 55,
      "method": "equi-height",
      "numbins": 100
    },
    {
      "id": 56,
      "method": "equi-height",
      "numbins": 100
    },
    {
      "id": 57,
      "method": "equi-height",
      "numbins": 100
    },
    {
      "id": 58,
      "method": "equi-height",
      "numbins": 100
    },
    {
      "id": 59,
      "method": "equi-height",
      "numbins": 100
    },
    {
      "id": 60,
      "method": "equi-height",
      "numbins": 100
    },
    {
      "id": 61,
      "method": "equi-height",
      "numbins": 100
    },
    {
      "id": 62,
      "method": "equi-height",
      "numbins": 100
    },
    {
      "id": 63,
      "method": "equi-height",
      "numbins": 100
    },
    {
      "id": 64,
      "method": "equi-height",
      "numbins": 100
    },
    {
      "id": 65,
      "method": "equi-height",
      "numbins": 100
    },
    {
      "id": 66,
      "method": "equi-height",
      "numbins": 100
    },
    {
      "id": 67,
      "method": "equi-height",
      "numbins": 100
    },
    {
      "id": 68,
      "method": "equi-height",
      "numbins": 100
    },
    {
      "id": 69,
      "method": "equi-height",
      "numbins": 100
    },
    {
      "id": 70,
      "method": "equi-height",
      "numbins": 100
    },
    {
      "id": 71,
      "method": "equi-height",
      "numbins": 100
    },
    {
      "id": 72,
      "method": "equi-height",
      "numbins": 100
    },
    {
      "id": 73,
      "method": "equi-height",
      "numbins": 100
    },
    {
      "id": 74,
      "method": "equi-height",
      "numbins": 100
    },
    {
      "id": 75,
      "method": "equi-height",
      "numbins": 100
    },
    {
      "id": 76,
      "method": "equi-height",
      "numbins": 100
    },
    {
      "id": 77,
      "method": "equi-height",
      "numbins": 100
    },
    {
      "id": 78,
      "method": "equi-height",
      "numbins": 100
    },
    {
      "id": 79,
      "method": "equi-height",
      "numbins": 100
    },
    {
      "id": 80,
      "method": "equi-height",
      "numbins": 100
    },
    {
      "id": 81,
      "method": "equi-height",
      "numbins": 100
    },
    {
      "id": 82,
      "method": "equi-height",
      "numbins": 100
    },
    {
      "id": 83,
      "method": "equi-height",
      "numbins": 100
    },
    {
      "id": 84,
      "method": "equi-height",
      "numbins": 100
    },
    {
      "id": 85,
      "method": "equi-height",
      "numbins": 100
    },
    {
      "id": 86,
      "method": "equi-height",
      "numbins": 100
    },
    {
      "id": 87,
      "method": "equi-height",
      "numbins": 100
    },
    {
      "id": 88,
      "method": "equi-height",
      "numbins": 100
    },
    {
      "id": 89,
      "method": "equi-height",
      "numbins": 100
    },
    {
      "id": 90,
      "method": "equi-height",
      "numbins": 100
    },
    {
      "id": 91,
      "method": "equi-height",
      "numbins": 100
    },
    {
      "id": 92,
      "method": "equi-height",
      "numbins": 100
    },
    {
      "id": 93,
      "method": "equi-height",
      "numbins": 100
    },
    {
      "id": 94,
      "method": "equi-height",
      "numbins": 100
    },
    {
      "id": 95,
      "method": "equi-height",
      "numbins": 100
    },
    {
      "id": 96,
      "method": "equi-height",
      "numbins": 100
    },
    {
      "id": 97,
      "method": "equi-height",
      "numbins": 100
    },
    {
      "id": 98,
      "method": "equi-height",
      "numbins": 100
    },
    {
      "id": 99,
      "method": "equi-height",
      "numbins": 100
    },
    {
      "id": 100,
      "method": "equi-height",
      "numbins": 100
    },
    {
      "id": 101,
      "method": "equi-height",
      "numbins": 100
    },
    {
      "id": 102,
      "method": "equi-height",
      "numbins": 100
    },
    {
      "id": 103,
      "method": "equi-height",
      "numbins": 100
    },
    {
      "id": 104,
      "method": "equi-height",
      "numbins": 100
    },
    {
      "id": 105,
      "method": "equi-height",
      "numbins": 100
    },
    {
      "id": 106,
      "method": "equi-height",
      "numbins": 100
    },
    {
      "id": 107,
      "method": "equi-height",
      "numbins": 100
    },
    {
      "id": 108,
      "method": "equi-height",
      "numbins": 100
    },
    {
      "id": 109,
      "method": "equi-height",
      "numbins": 100
    },
    {
      "id": 110,
      "method": "equi-height",
      "numbins": 100
    },
    {
      "id": 111,
      "method": "equi-height",
      "numbins": 100
    },
    {
      "id": 112,
      "method": "equi-height",
      "numbins": 100
    },
    {
      "id": 113,
      "method": "equi-height",
      "numbins": 100
    },
    {
      "id": 114,
      "method": "equi-height",
      "numbins": 100
    },
    {
      "id": 115,
      "method": "equi-height",
      "numbins": 100
    },
    {
      "id": 116,
      "method": "equi-height",
      "numbins": 100
    },
    {
      "id": 117,
      "method": "equi-height",
      "numbins": 100
    },
    {
      "id": 118,
      "method": "equi-height",
      "numbins": 100
    },
    {
      "id": 119,
      "method": "equi-height",
      "numbins": 100
    },
    {
      "id": 120,
      "method": "equi-height",
      "numbins": 100
    },
    {
      "id": 121,
      "method": "equi-height",
      "numbins": 100
    },
    {
      "id": 122,
      "method": "equi-height",
      "numbins": 100
    },
    {
      "id": 123,
      "method": "equi-height",
      "numbins": 100
    },
    {
      "id": 124,
      "method": "equi-height",
      "numbins": 100
    },
    {
      "id": 125,
      "method": "equi-height",
      "numbins": 100
    },
    {
      "id": 126,
      "method": "equi-height",
      "numbins": 100
    },
    {
      "id": 127,
      "method": "equi-height",
      "numbins": 100
    },
    {
      "id": 128,
      "method": "equi-height",
      "numbins": 100
    },
    {
      "id": 129,
      "method": "equi-height",
      "numbins": 100
    },
    {
      "id": 130,
      "method": "equi-height",
      "numbins": 100
    },
    {
      "id": 131,
      "method": "equi-height",
      "numbins": 100
    },
    {
      "id": 132,
      "method": "equi-height",
      "numbins": 100
    },
    {
      "id": 133,
      "method": "equi-height",
      "numbins": 100
    },
    {
      "id": 134,
      "method": "equi-height",
      "numbins": 100
    },
    {
      "id": 135,
      "method": "equi-height",
      "numbins": 100
    },
    {
      "id": 136,
      "method": "equi-height",
      "numbins": 100
    },
    {
      "id": 137,
      "method": "equi-height",
      "numbins": 100
    },
    {
      "id": 138,
      "method": "equi-height",
      "numbins": 100
    },
    {
      "id": 139,
      "method": "equi-height",
      "numbins": 100
    },
    {
      "id": 140,
      "method": "equi-height",
      "numbins": 100
    },
    {
      "id": 141,
      "method": "equi-height",
      "numbins": 100
    },
    {
      "id": 142,
      "method": "equi-height",
      "numbins": 100
    },
    {
      "id": 143,
      "method": "equi-height",
      "numbins": 100
    },
    {
      "id": 144,
      "method": "equi-height",
      "numbins": 100
    },
    {
      "id": 145,
      "method": "equi-height",
      "numbins": 100
    },
    {
      "id": 146,
      "method": "equi-height",
      "numbins": 100
    },
    {
      "id": 147,
      "method": "equi-height",
      "numbins": 100
    },
    {
      "id": 148,
      "method": "equi-height",
      "numbins": 100
    },
    {
      "id": 149,
      "method": "equi-height",
      "numbins": 100
    },
    {
      "id": 150,
      "method": "equi-height",
      "numbins": 100
    },
    {
      "id": 151,
      "method": "equi-height",
      "numbins": 100
    },
    {
      "id": 152,
      "method": "equi-height",
      "numbins": 100
    },
    {
      "id": 153,
      "method": "equi-height",
      "numbins": 100
    },
    {
      "id": 154,
      "method": "equi-height",
      "numbins": 100
    },
    {
      "id": 155,
      "method": "equi-height",
      "numbins": 100
    },
    {
      "id": 156,
      "method": "equi-height",
      "numbins": 100
    },
    {
      "id": 157,
      "method": "equi-height",
      "numbins": 100
    },
    {
      "id": 158,
      "method": "equi-height",
      "numbins": 100
    },
    {
      "id": 159,
      "method": "equi-height",
      "numbins": 100
    },
    {
      "id": 160,
      "method": "equi-height",
      "numbins": 100
    },
    {
      "id": 161,
      "method": "equi-height",
      "numbins": 100
    },
    {
      "id": 162,
      "method": "equi-height",
      "numbins": 100
    },
    {
      "id": 163,
      "method": "equi-height",
      "numbins": 100
    },
    {
      "id": 164,
      "method": "equi-height",
      "numbins": 100
    },
    {
      "id": 165,
      "method": "equi-height",
      "numbins": 100
    },
    {
      "id": 166,
      "method": "equi-height",
      "numbins": 100
    },
    {
      "id": 167,
      "method": "equi-height",
      "numbins": 100
    },
    {
      "id": 168,
      "method": "equi-height",
      "numbins": 100
    },
    {
      "id": 169,
      "method": "equi-height",
      "numbins": 100
    },
    {
      "id": 170,
      "method": "equi-height",
      "numbins": 100
    },
    {
      "id": 171,
      "method": "equi-height",
      "numbins": 100
    },
    {
      "id": 172,
      "method": "equi-height",
      "numbins": 100
    },
    {
      "id": 173,
      "method": "equi-height",
      "numbins": 100
    },
    {
      "id": 174,
      "method": "equi-height",
      "numbins": 100
    },
    {
      "id": 175,
      "method": "equi-height",
      "numbins": 100
    },
    {
      "id": 176,
      "method": "equi-height",
      "numbins": 100
    },
    {
      "id": 177,
      "method": "equi-height",
      "numbins": 100
    },
    {
      "id": 178,
      "method": "equi-height",
      "numbins": 100
    },
    {
      "id": 179,
      "method": "equi-height",
      "numbins": 100
    },
    {
      "id": 180,
      "method": "equi-height",
      "numbins": 100
    },
    {
      "id": 181,
      "method": "equi-height",
      "numbins": 100
    },
    {
      "id": 182,
      "method": "equi-height",
      "numbins": 100
    },
    {
      "id": 183,
      "method": "equi-height",
      "numbins": 100
    },
    {
      "id": 184,
      "method": "equi-height",
      "numbins": 100
    },
    {
      "id": 185,
      "method": "equi-height",
      "numbins": 100
    },
    {
      "id": 186,
      "method": "equi-height",
      "numbins": 100
    },
    {
      "id": 187,
      "method": "equi-height",
      "numbins": 100
    },
    {
      "id": 188,
      "method": "equi-height",
      "numbins": 100
    },
    {
      "id": 189,
      "method": "equi-height",
      "numbins": 100
    },
    {
      "id": 190,
      "method": "equi-height",
      "numbins": 100
    },
    {
      "id": 191,
      "method": "equi-height",
      "numbins": 100
    },
    {
      "id": 192,
      "method": "equi-height",
      "numbins": 100
    },
    {
      "id": 193,
      "method": "equi-height",
      "numbins": 100
    },
    {
      "id": 194,
      "method": "equi-height",
      "numbins": 100
    },
    {
      "id": 195,
      "method": "equi-height",
      "numbins": 100
    },
    {
      "id": 196,
      "method": "equi-height",
      "numbins": 100
    },
    {
      "id": 197,
      "method": "equi-height",
      "numbins": 100
    },
    {
      "id": 198,
      "method": "equi-height",
      "numbins": 100
    },
    {
      "id": 199,
      "method": "equi-height",
      "numbins": 100
    },
    {
      "id": 200,
      "method": "equi-height",
      "numbins": 100
    },
    {
      "id": 201,
      "method": "equi-height",
      "numbins": 100
    }
  ]
}